paprika_to_sqlite
