Metadata-Version: 2.1
Name: paprika-to-sqlite
Version: 0.2.1
Summary: Convert Paprika Recipes files into a SQLite database
Home-page: https://github.com/gerrymanoim/paprika-to-sqlite
Author: Gerry Manoim
Author-email: Gerry Manoim <gerrymanoim@gmail.com>
License: Apache License, Version 2.0
Platform: UNKNOWN
Classifier: Intended Audience :: Developers
Classifier: Intended Audience :: Science/Research
Classifier: Intended Audience :: End Users/Desktop
Classifier: Topic :: Database
Classifier: License :: OSI Approved :: Apache Software License
Classifier: Programming Language :: Python :: 3.6
Provides-Extra: datasette
Provides-Extra: dev
